reportWaysonQi123/HTMLTestRunner.py
reportWaysonQi123/PyTestReportPlug.py
reportWaysonQi123/SendEmail.py
reportWaysonQi123/__init__.py
reportWaysonQi123/api.py
reportWaysonQi123/static/css/default.css
reportWaysonQi123/static/css/legency.css
reportWaysonQi123/static/js/capture.js
reportWaysonQi123/static/js/default.js
reportWaysonQi123/static/js/legency.js
reportWaysonQi123/templates/default.html
reportWaysonQi123/templates/legency.html
reportWaysonQi123-1.0.3.data/data/capture.js
reportWaysonQi123-1.0.3.data/data/default.css
reportWaysonQi123-1.0.3.data/data/default.html
reportWaysonQi123-1.0.3.data/data/default.js
reportWaysonQi123-1.0.3.data/data/legency.css
reportWaysonQi123-1.0.3.data/data/legency.html
reportWaysonQi123-1.0.3.data/data/legency.js
reportWaysonQi123-1.0.3.dist-info/LICENCE
reportWaysonQi123-1.0.3.dist-info/METADATA
reportWaysonQi123-1.0.3.dist-info/WHEEL
reportWaysonQi123-1.0.3.dist-info/entry_points.txt
reportWaysonQi123-1.0.3.dist-info/top_level.txt
reportWaysonQi123-1.0.3.dist-info/RECORD
