Metadata-Version: 2.1
Name: reportWaysonQi123
Version: 1.0.3
Summary: UNKNOWN
Home-page: 
Author: 
Author-email: 
License: UNKNOWN
Keywords: test report,python unit testing
Platform: any
Classifier: Programming Language :: Python :: 3
Classifier: License :: OSI Approved :: MIT License
Classifier: Operating System :: OS Independent
Classifier: Framework :: Pytest
License-File: LICENCE
Requires-Dist: Jinja2 (==2.10)
Requires-Dist: Flask (==1.0.2)
Requires-Dist: MarkupSafe (==2.0.1)
